odoo/addons/document_page_environment_manual/README.rst
odoo/addons/document_page_environment_manual/__init__.py
odoo/addons/document_page_environment_manual/__manifest__.py
odoo/addons/document_page_environment_manual/data/document_page_environment_manual.xml
odoo/addons/document_page_environment_manual/i18n/de.po
odoo/addons/document_page_environment_manual/i18n/document_page_environment_manual.pot
odoo/addons/document_page_environment_manual/i18n/fr.po
odoo/addons/document_page_environment_manual/i18n/it.po
odoo/addons/document_page_environment_manual/i18n/nb.po
odoo/addons/document_page_environment_manual/i18n/pt_BR.po
odoo/addons/document_page_environment_manual/i18n/sl.po
odoo/addons/document_page_environment_manual/i18n/sv.po
odoo/addons/document_page_environment_manual/i18n/vi.po
odoo/addons/document_page_environment_manual/readme/CONTRIBUTORS.rst
odoo/addons/document_page_environment_manual/readme/DESCRIPTION.rst
odoo/addons/document_page_environment_manual/readme/USAGE.rst
odoo/addons/document_page_environment_manual/static/description/icon.png
odoo/addons/document_page_environment_manual/static/description/index.html
odoo14_addon_document_page_environment_manual-14.0.1.0.1.dev7.dist-info/METADATA
odoo14_addon_document_page_environment_manual-14.0.1.0.1.dev7.dist-info/WHEEL
odoo14_addon_document_page_environment_manual-14.0.1.0.1.dev7.dist-info/top_level.txt
odoo14_addon_document_page_environment_manual-14.0.1.0.1.dev7.dist-info/RECORD
